condorai/__init__.py
condorai/_version.py
condorai/py.typed
condorai-0.2.0.dist-info/METADATA
condorai-0.2.0.dist-info/WHEEL
condorai-0.2.0.dist-info/licenses/LICENSE
condorai-0.2.0.dist-info/RECORD
